shared_context_server/__init__.py
shared_context_server/admin_guidance.py
shared_context_server/admin_lifecycle.py
shared_context_server/admin_resources.py
shared_context_server/admin_tools.py
shared_context_server/auth.py
shared_context_server/auth_context.py
shared_context_server/auth_core.py
shared_context_server/auth_core_context.py
shared_context_server/auth_secure.py
shared_context_server/auth_tools.py
shared_context_server/config.py
shared_context_server/config_context.py
shared_context_server/core_server.py
shared_context_server/database.py
shared_context_server/database_manager.py
shared_context_server/database_sqlalchemy.py
shared_context_server/database_testing.py
shared_context_server/memory_tools.py
shared_context_server/models.py
shared_context_server/models_core.py
shared_context_server/models_requests.py
shared_context_server/models_utilities.py
shared_context_server/prompts.py
shared_context_server/py.typed
shared_context_server/resources.py
shared_context_server/search_tools.py
shared_context_server/server.py
shared_context_server/session_tools.py
shared_context_server/test_database_context.py
shared_context_server/tools.py
shared_context_server/web_endpoints.py
shared_context_server/websocket_handlers.py
shared_context_server/websocket_server.py
shared_context_server/config/README.md
shared_context_server/config/agent_permissions.json
shared_context_server/config/agent_permissions_schema.json
shared_context_server/scripts/__init__.py
shared_context_server/scripts/cli.py
shared_context_server/scripts/dev.py
shared_context_server/static/css/style.css
shared_context_server/static/js/app.js
shared_context_server/templates/base.html
shared_context_server/templates/dashboard.html
shared_context_server/templates/memory.html
shared_context_server/templates/session_view.html
shared_context_server/utils/__init__.py
shared_context_server/utils/caching.py
shared_context_server/utils/llm_errors.py
shared_context_server/utils/performance.py
shared_context_server-1.1.10.dist-info/METADATA
shared_context_server-1.1.10.dist-info/WHEEL
shared_context_server-1.1.10.dist-info/entry_points.txt
shared_context_server-1.1.10.dist-info/licenses/LICENSE
shared_context_server-1.1.10.dist-info/RECORD
