Metadata-Version: 2.4
Name: shared-context-server
Version: 1.1.10
Summary: Shared Context MCP Server for multi-agent collaboration
Project-URL: Homepage, https://github.com/shared-context-server/shared-context-server
Project-URL: Documentation, https://shared-context-server.readthedocs.io
Project-URL: Repository, https://github.com/shared-context-server/shared-context-server.git
Project-URL: Issues, https://github.com/shared-context-server/shared-context-server/issues
Author: Shared Context Server Team
License: MIT
License-File: LICENSE
Classifier: Development Status :: 4 - Beta
Classifier: Intended Audience :: Developers
Classifier: License :: OSI Approved :: MIT License
Classifier: Programming Language :: Python :: 3
Classifier: Programming Language :: Python :: 3.10
Classifier: Programming Language :: Python :: 3.11
Classifier: Programming Language :: Python :: 3.12
Classifier: Programming Language :: Python :: 3.13
Classifier: Topic :: Software Development :: Libraries :: Python Modules
Classifier: Topic :: System :: Distributed Computing
Requires-Python: >=3.10
Requires-Dist: aiosqlite>=0.20.0
Requires-Dist: asyncpg>=0.29.0
Requires-Dist: cryptography>=3.4.8
Requires-Dist: fastapi>=0.100.0
Requires-Dist: fastmcp>=2.11.3
Requires-Dist: greenlet>=3.2.4
Requires-Dist: httpx>=0.25.0
Requires-Dist: jinja2>=3.1.0
Requires-Dist: mcpsock>=0.1.5
Requires-Dist: pydantic-settings>=2.0.0
Requires-Dist: pydantic>=2.0.0
Requires-Dist: pyjwt>=2.8.0
Requires-Dist: python-dotenv>=1.0.0
Requires-Dist: python-multipart>=0.0.6
Requires-Dist: rapidfuzz>=3.0.0
Requires-Dist: requests>=2.31.0
Requires-Dist: sqlalchemy>=2.0.43
Requires-Dist: typing-extensions>=4.0.0
Requires-Dist: uvicorn[standard]>=0.35.0
Requires-Dist: watchdog>=6.0.0
Requires-Dist: websockets>=13.0
Provides-Extra: all-databases
Requires-Dist: aiomysql>=0.2.0; extra == 'all-databases'
Requires-Dist: asyncpg>=0.29.0; extra == 'all-databases'
Provides-Extra: dev
Requires-Dist: mypy>=1.0.0; extra == 'dev'
Requires-Dist: pre-commit>=3.0.0; extra == 'dev'
Requires-Dist: pytest-asyncio>=0.21.0; extra == 'dev'
Requires-Dist: pytest-cov>=4.0.0; extra == 'dev'
Requires-Dist: pytest>=7.0.0; extra == 'dev'
Requires-Dist: ruff>=0.1.0; extra == 'dev'
Provides-Extra: docs
Requires-Dist: mkdocs-material>=9.0.0; extra == 'docs'
Requires-Dist: mkdocs>=1.5.0; extra == 'docs'
Requires-Dist: mkdocstrings[python]>=0.20.0; extra == 'docs'
Provides-Extra: mysql
Requires-Dist: aiomysql>=0.2.0; extra == 'mysql'
Provides-Extra: postgresql
Provides-Extra: test
Requires-Dist: httpx>=0.25.0; extra == 'test'
Requires-Dist: pytest-asyncio>=0.21.0; extra == 'test'
Requires-Dist: pytest-cov>=4.0.0; extra == 'test'
Requires-Dist: pytest>=7.0.0; extra == 'test'
